Metadata-Version: 2.1
Name: saltclass
Version: 0.2.1
Summary: Short and Long Text Classifier using clustering-based enrichment
Home-page: https://github.com/bagheria/saltclass
Author: Ayoub Bagheri
Author-email: ayoub.bagheri@gmail.com
License: MIT
Keywords: short text classification
Platform: UNKNOWN
